prefect_aws/__init__.py
prefect_aws/_version.py
prefect_aws/assume_role_parameters.py
prefect_aws/batch.py
prefect_aws/client_parameters.py
prefect_aws/client_waiter.py
prefect_aws/credentials.py
prefect_aws/glue_job.py
prefect_aws/lambda_function.py
prefect_aws/plugins.py
prefect_aws/py.typed
prefect_aws/s3.py
prefect_aws/secrets_manager.py
prefect_aws/settings.py
prefect_aws/utilities.py
prefect_aws/_cli/__init__.py
prefect_aws/_cli/ecs_worker.py
prefect_aws/_cli/main.py
prefect_aws/_cli/utils.py
prefect_aws/deployments/__init__.py
prefect_aws/deployments/steps.py
prefect_aws/experimental/__init__.py
prefect_aws/experimental/decorators.py
prefect_aws/experimental/bundles/__init__.py
prefect_aws/experimental/bundles/execute.py
prefect_aws/experimental/bundles/upload.py
prefect_aws/observers/ecs.py
prefect_aws/templates/__init__.py
prefect_aws/templates/ecs/__init__.py
prefect_aws/templates/ecs/events-only.json
prefect_aws/templates/ecs/service.json
prefect_aws/workers/__init__.py
prefect_aws/workers/ecs_worker.py
prefect_aws-0.7.3.dist-info/licenses/LICENSE
prefect_aws-0.7.3.dist-info/METADATA
prefect_aws-0.7.3.dist-info/WHEEL
prefect_aws-0.7.3.dist-info/entry_points.txt
prefect_aws-0.7.3.dist-info/top_level.txt
prefect_aws-0.7.3.dist-info/RECORD
