Metadata-Version: 2.4
Name: prefect-aws
Version: 0.7.3
Summary: Prefect integrations for interacting with Amazon Web Services.
Author-email: "Prefect Technologies, Inc." <help@prefect.io>
License: Apache License 2.0
Project-URL: Homepage, https://github.com/PrefectHQ/prefect/tree/main/src/integrations/prefect-aws
Keywords: prefect
Classifier: Natural Language :: English
Classifier: Intended Audience :: Developers
Classifier: Intended Audience :: System Administrators
Classifier: License :: OSI Approved :: Apache Software License
Classifier: Programming Language :: Python :: 3 :: Only
Classifier: Programming Language :: Python :: 3.10
Classifier: Programming Language :: Python :: 3.11
Classifier: Programming Language :: Python :: 3.12
Classifier: Programming Language :: Python :: 3.13
Classifier: Topic :: Software Development :: Libraries
Requires-Python: >=3.10
License-File: LICENSE
Requires-Dist: aiobotocore>=2.23.2
Requires-Dist: boto3>=1.24.53
Requires-Dist: botocore>=1.27.53
Requires-Dist: prefect>=3.4.7
Requires-Dist: pyparsing>=3.1.1
Requires-Dist: tenacity>=8.0.0
Requires-Dist: typer>=0.9.0
Requires-Dist: rich>=10.0.0
Dynamic: license-file
